kdelikelihood/__init__.py
kdelikelihood/_kde_tools.cp311-win_amd64.pdb
kdelikelihood/_kde_tools.cp311-win_amd64.pyd
kdelikelihood/_kde_tools.cpp
kdelikelihood/_kde_tools.pxd
kdelikelihood/_kde_tools.pyx
kdelikelihood/_kde_tools_internals.h
kdelikelihood/analyze.py
kdelikelihood/kdelikelihood.py
kdelikelihood/optimize.py
kdelikelihood-0.2.1.dist-info/LICENSE
kdelikelihood-0.2.1.dist-info/METADATA
kdelikelihood-0.2.1.dist-info/WHEEL
kdelikelihood-0.2.1.dist-info/top_level.txt
kdelikelihood-0.2.1.dist-info/RECORD
