Metadata-Version: 2.1
Name: kdelikelihood
Version: 0.2.1
Summary: A python package to compute kernel-density-estimated likelihood
Home-page: https://git.ufz.de/fischsam/kde-likelihood
Author: Samuel M. Fischer
Author-email: samuel.fischer@ufz.de
License: GNU Lesser General Public License v3 (LGPLv3)
Classifier: Programming Language :: Python :: 3
Classifier: License :: OSI Approved :: GNU Lesser General Public License v3 (LGPLv3)
Classifier: Operating System :: OS Independent
License-File: LICENSE
Requires-Dist: numpy >=1.23
Requires-Dist: scipy
Requires-Dist: matplotlib
Requires-Dist: py-bobyqa
Requires-Dist: objectproxypool
